rabbitpy/__init__.py
rabbitpy/amqp.py
rabbitpy/amqp_queue.py
rabbitpy/base.py
rabbitpy/channel.py
rabbitpy/channel0.py
rabbitpy/connection.py
rabbitpy/events.py
rabbitpy/exceptions.py
rabbitpy/exchange.py
rabbitpy/heartbeat.py
rabbitpy/io.py
rabbitpy/message.py
rabbitpy/simple.py
rabbitpy/tx.py
rabbitpy/utils.py
rabbitpy-2.0.0.dist-info/LICENSE
rabbitpy-2.0.0.dist-info/METADATA
rabbitpy-2.0.0.dist-info/WHEEL
rabbitpy-2.0.0.dist-info/top_level.txt
rabbitpy-2.0.0.dist-info/zip-safe
rabbitpy-2.0.0.dist-info/RECORD
